{
  "Estudante": [
    {
      "id": 1,
      "name": "Sérgio Pato",
      "idade": 34,
      "curso": "Direito",
      "semestre": "4"
    },
    {
      "id": 2,
      "name": "Josiane Frias",
      "idade": 19,
      "curso": "ADS",
      "semestre": "2"
    },
    {
      "id": 3,
      "name": "Jorge Dalmastti",
      "idade": 22,
      "curso": "Economia",
      "semestre": "3"
    },
    {
      "id": 3,
      "name": "Emílio Camelo",
      "idade": 20,
      "curso": "Astronomia",
      "semestre": "6"
    },
    {
      "id": 4,
      "name": "Edson Marques",
      "idade": 23,
      "curso": "Psicologia",
      "semestre": "2"
    },
    {
      "id": 5,
      "name": "Marisia Vertunni",
      "idade": 21,
      "curso": "Odontologia",
      "semestre": "1"
    },
    {
      "id": 6,
      "name": "Thiago Abravanull",
      "idade": 48,
      "curso": "Ciência de dados",
      "semestre": "2"
    },
    {
      "id": 7,
      "name": "Joyce Warren",
      "idade": 25,
      "curso": "Teologia",
      "semestre": "3"
    },
    {
      "id": 7,
      "name": "Larissa Ferraz",
      "idade": 18,
      "curso": "Letras",
      "semestre": "1"
    },
    {
      "id": 7,
      "name": "Boris Spederson",
      "idade": 24,
      "curso": "Enfermagem",
      "semestre": "7"
    },
    {
      "name": "Glauco Tobespo",
      "id": 8
    },
    {
      "name": "Felipão Comuna",
      "id": 9
    },
    {
      "name": "46146ty4",
      "id": 10
    },
    {
      "name": "Alex",
      "id": 11
    }
  ]
}